{
    "last_updated": "2026-05-30T21:33:56.856658",
    "total_listening_time": "16h 23m",
    "top_artists_weekly": [
        {
            "artist_name": "Quadeca",
            "plays": 95
        },
        {
            "artist_name": "glaive",
            "plays": 20
        },
        {
            "artist_name": "Kane Parsons",
            "plays": 16
        },
        {
            "artist_name": "Earl Sweatshirt",
            "plays": 13
        },
        {
            "artist_name": "brakence",
            "plays": 10
        }
    ],
    "top_tracks_weekly": [
        {
            "track_name": "Dark Magic",
            "artist_name": "Quadeca",
            "plays": 85
        },
        {
            "track_name": "rosier/punk2",
            "artist_name": "brakence",
            "plays": 6
        },
        {
            "track_name": "numb",
            "artist_name": "Bayymack",
            "plays": 3
        },
        {
            "track_name": "Goals",
            "artist_name": "Sophie Powers",
            "plays": 2
        },
        {
            "track_name": "Why Did I Laugh Anyway",
            "artist_name": "Dev Lemons",
            "plays": 2
        }
    ],
    "top_albums_weekly": [
        {
            "album_name": "Dark Magic",
            "artist_name": "Quadeca",
            "plays": 85
        },
        {
            "album_name": "Y\u2019all",
            "artist_name": "glaive",
            "plays": 17
        },
        {
            "album_name": "Backrooms (Original Score), Vol. 3",
            "artist_name": "Kane Parsons",
            "plays": 16
        },
        {
            "album_name": "Live Laugh Love",
            "artist_name": "Earl Sweatshirt",
            "plays": 12
        },
        {
            "album_name": "EXPERIMENTAL RAP",
            "artist_name": "JPEGMAFIA",
            "plays": 7
        }
    ]
}