{
    "last_updated": "2026-05-24T10:19:45.230649",
    "total_listening_time": "13h 0m",
    "top_artists_weekly": [
        {
            "artist_name": "Forrest Nolan",
            "plays": 8
        },
        {
            "artist_name": "Quadeca",
            "plays": 7
        },
        {
            "artist_name": "Dmitri Shostakovich",
            "plays": 7
        },
        {
            "artist_name": "Eric Christian",
            "plays": 4
        },
        {
            "artist_name": "Knxwledge",
            "plays": 4
        }
    ],
    "top_tracks_weekly": [
        {
            "track_name": "thank you i guess",
            "artist_name": "Forrest Nolan",
            "plays": 8
        },
        {
            "track_name": "itkanbe[sonice]",
            "artist_name": "Knxwledge",
            "plays": 4
        },
        {
            "track_name": "Missing Piece",
            "artist_name": "John Michael Howell",
            "plays": 4
        },
        {
            "track_name": "TOO COOL TO BE CARELESS",
            "artist_name": "PAWSA",
            "plays": 3
        },
        {
            "track_name": "False Reaction",
            "artist_name": "VIOLENT VIRA",
            "plays": 3
        }
    ],
    "top_albums_weekly": [
        {
            "album_name": "thank you i guess",
            "artist_name": "Forrest Nolan",
            "plays": 8
        },
        {
            "album_name": "1988",
            "artist_name": "Knxwledge",
            "plays": 4
        },
        {
            "album_name": "Shostakovich: Jazz Suites Nos. 1 - 2 / The Bolt / Tahiti Trot",
            "artist_name": "Dmitri Shostakovich",
            "plays": 4
        },
        {
            "album_name": "Missing Piece",
            "artist_name": "John Michael Howell",
            "plays": 4
        },
        {
            "album_name": "False Reaction",
            "artist_name": "VIOLENT VIRA",
            "plays": 3
        }
    ]
}